<?xml version='1.0' encoding='UTF-8' standalone='yes' ?>
<trigger-manifest version="1.0">
  <onTrigger action ="countrySwitch">
    <featureList value="AE" folder="AE"/>
    <featureList value="AF" folder="AF"/>
    <featureList value="AR" folder="AR"/>
    <featureList value="AT" folder="AT"/>
    <featureList value="AU" folder="AU"/>
    <featureList value="AZ" folder="AZ"/>
    <featureList value="BA" folder="BA"/>
    <featureList value="BD" folder="BD"/>
    <featureList value="BE" folder="BE"/>
    <featureList value="BG" folder="BG"/>
    <featureList value="BH" folder="BH"/>
    <featureList value="BO" folder="BO"/>
    <featureList value="BR" folder="BR"/>
    <featureList value="CH" folder="CH"/>
    <featureList value="CN" folder="CN"/>
    <featureList value="CO" folder="CO"/>
    <featureList value="CR" folder="CR"/>
    <featureList value="CZ" folder="CZ"/>
    <featureList value="DE" folder="DE"/>
    <featureList value="DK" folder="DK"/>
    <featureList value="DM" folder="DM"/>
    <featureList value="DO" folder="DO"/>
    <featureList value="DZ" folder="DZ"/>
    <featureList value="EC" folder="EC"/>
    <featureList value="EE" folder="EE"/>
    <featureList value="EG" folder="EG"/>
    <featureList value="ES" folder="ES"/>
    <featureList value="FI" folder="FI"/>
    <featureList value="FR" folder="FR"/>
    <featureList value="GB" folder="GB"/>
    <featureList value="GH" folder="GH"/>
    <featureList value="GR" folder="GR"/>
    <featureList value="HK" folder="HK"/>
    <featureList value="HN" folder="HN"/>
    <featureList value="HR" folder="HR"/>
    <featureList value="HU" folder="HU"/>
    <featureList value="ID" folder="ID"/>
    <featureList value="IE" folder="IE"/>
    <featureList value="IL" folder="IL"/>
    <featureList value="IN" folder="IN"/>
    <featureList value="IQ" folder="IQ"/>
    <featureList value="IR" folder="IR"/>
    <featureList value="IS" folder="IS"/>
    <featureList value="IT" folder="IT"/>
    <featureList value="JO" folder="JO"/>
    <featureList value="JP" folder="JP"/>
    <featureList value="KE" folder="KE"/>
    <featureList value="KH" folder="KH"/>
    <featureList value="KR" folder="KR"/>
    <featureList value="KW" folder="KW"/>
    <featureList value="KZ" folder="KZ"/>
    <featureList value="LA" folder="LA"/>
    <featureList value="LB" folder="LB"/>
    <featureList value="LK" folder="LK"/>
    <featureList value="LU" folder="LU"/>
    <featureList value="MA" folder="MA"/>
    <featureList value="ME" folder="ME"/>
    <featureList value="MK" folder="MK"/>
    <featureList value="MM" folder="MM"/>
    <featureList value="MT" folder="MT"/>
    <featureList value="MX" folder="MX"/>
    <featureList value="MY" folder="MY"/>
    <featureList value="NG" folder="NG"/>
    <featureList value="NL" folder="NL"/>
    <featureList value="NO" folder="NO"/>
    <featureList value="NP" folder="NP"/>
    <featureList value="NZ" folder="NZ"/>
    <featureList value="OC" folder="OC"/>
    <featureList value="OM" folder="OM"/>
    <featureList value="PA" folder="PA"/>
    <featureList value="PH" folder="PH"/>
    <featureList value="PK" folder="PK"/>
    <featureList value="PL" folder="PL"/>
    <featureList value="PS" folder="PS"/>
    <featureList value="PT" folder="PT"/>
    <featureList value="QA" folder="QA"/>
    <featureList value="RO" folder="RO"/>
    <featureList value="RS" folder="RS"/>
    <featureList value="RU" folder="RU"/>
    <featureList value="SA" folder="SA"/>
    <featureList value="SE" folder="SE"/>
    <featureList value="SG" folder="SG"/>
    <featureList value="SK" folder="SK"/>
    <featureList value="SV" folder="SV"/>
    <featureList value="SY" folder="SY"/>
    <featureList value="TH" folder="TH"/>
    <featureList value="TN" folder="TN"/>
    <featureList value="TR" folder="TR"/>
    <featureList value="TW" folder="TW"/>
    <featureList value="UA" folder="UA"/>
    <featureList value="US" folder="US"/>
    <featureList value="UY" folder="UY"/>
    <featureList value="UZ" folder="UZ"/>
    <featureList value="VE" folder="VE"/>
    <featureList value="VN" folder="VN"/>
    <featureList value="XK" folder="XK"/>
    <featureList value="YE" folder="YE"/>
    <featureList value="ZA" folder="ZA"/>
  </onTrigger>
</trigger-manifest>
